odoo10_addon_mail_embed_image-10.0.1.0.1-py3.8-nspkg.pth
odoo/addons/mail_embed_image/README.rst
odoo/addons/mail_embed_image/__init__.py
odoo/addons/mail_embed_image/__manifest__.py
odoo/addons/mail_embed_image/i18n/mail_embed_image.pot
odoo/addons/mail_embed_image/models/__init__.py
odoo/addons/mail_embed_image/models/ir_mail_server.py
odoo/addons/mail_embed_image/readme/CONTRIBUTORS.rst
odoo/addons/mail_embed_image/readme/DESCRIPTION.rst
odoo/addons/mail_embed_image/static/description/icon.png
odoo/addons/mail_embed_image/static/description/index.html
odoo/addons/mail_embed_image/tests/__init__.py
odoo/addons/mail_embed_image/tests/test_mail_embed_image.py
odoo10_addon_mail_embed_image-10.0.1.0.1.dist-info/METADATA
odoo10_addon_mail_embed_image-10.0.1.0.1.dist-info/WHEEL
odoo10_addon_mail_embed_image-10.0.1.0.1.dist-info/namespace_packages.txt
odoo10_addon_mail_embed_image-10.0.1.0.1.dist-info/top_level.txt
odoo10_addon_mail_embed_image-10.0.1.0.1.dist-info/RECORD
